{
   "packages":[
      {
         "name":"Qduino Mini",
         "maintainer":"Qtechknow",
         "websiteURL":"https://SparkFun.com",
         "email":"TechSupport@SparkFun.com",
         "help":{
            "online":"https://forum.sparkfun.com"
         },
         "platforms":[
            {
               "name":"Qtechknow Boards",
               "architecture":"avr",
               "version":"1.0.0",
               "category":"Qtechknow",
               "url":"http://nocotriathlon.com/3cvnev9er/qduinomini.tar.bz2",
               "archiveFileName":"qduinomini.tar.bz2",
               "checksum":"SHA-256:74c32efbc4b9d845d1a7c1246eb820cf43df4e606f0e169a2a60f55ddc4469d8",
               "size":"24912",
               "help":{
                  "online":"https://forums.sparkfun.com"
               },
               "boards":[
                  {
                     "name":"Qduino Mini"
                  }
               ],
               "toolsDependencies":[
                  {
                     "packager":"arduino",
                     "name":"avr-gcc",
                     "version":"4.8.1-arduino5"
                  },
                  {
                     "packager":"arduino",
                     "name":"avrdude",
                     "version":"6.0.1-arduino5"
                  }
               ]
            }
         ],
         "tools":[]
      }
   ]
}
